[{"fromVerse": 1, "toVerse": 1, "text": "<p>আলিফ লা-ম মী-ম।</p>"}, {"fromVerse": 2, "toVerse": 2, "text": "<p>আল্লাহ ব্যতীত অন্য কোন (সত্য) উপাস্য নেই, তিনি চিরঞ্জীব ও সব কিছুর ধারক। [১]</p><p>[১] حَيٌّ এবং قَيُّومٌ মহান আল্লাহর বিশেষ গুণ। 'হায়্যুন'এর অর্থ তিনি চিরঞ্জীব, তাঁর মৃত্যু ও ধ্বংস নেই। 'ক্বায়্যুম'এর অর্থ, তিনি নিখিল বিশ্বের ধারক, সংরক্ষণকারী এবং পর্যবেক্ষক। বিশ্বের সব কিছুই তাঁর মুখাপেক্ষী, তিনি কারো মুখাপেক্ষী নন। খ্রিষ্টানরা ঈসা (আঃ)-কে আল্লাহ অথবা তাঁর পুত্র কিংবা তিনের এক মনে করত। সুতরাং তাদেরকে বলা হচ্ছে যে, ঈসা (আঃ)ও যখন আল্লাহর সৃষ্টি, তিনি মায়ের পেট থেকে জন্ম নিয়েছেন এবং তাঁর জন্মকালও পৃথিবী সৃষ্টির বহুকাল পর। তাহলে তিনি আল্লাহ অথবা তাঁর পুত্র কিভাবে হতে পারেন? যদি তোমাদের বিশ্বাস সঠিক হত, তাহলে সে সৃষ্টি হয়ে তাকে ইলাহী গুণের অধিকারী এবং অনাদি হওয়া উচিত ছিল। অনুরূপ তাঁর উপর মৃত্যু আসাও উচিত নয়, কিন্তু এমন এক সময় আসবে যখন মৃত্যু তাঁকে গ্রাস করবে। আর খ্রিষ্টানদের ধারণা অনুযায়ী তিনি তো মারাই গেছেন। বহু হাদীসে এসেছে যে, আল্লাহর ইসমে আ'যম (মহান নাম) তিনটি আয়াতে এসেছে। কেউ যদি এই নামের অসীলায় দু'আ করে, তাহলে তা প্রত্যাখ্যাত হয় না। এক তো এই সূরা আলে-ইমরানে। দ্বিতীয় আয়াতুল কুরসীতে [اللهُ لا إِلَهَ إِلَّا هُوَ الْحَيُّ الْقَيُّومُ] এবং তৃতীয় সূরা ত্বাহাতে [وَعَنَتِ الْوُجُوهُ لِلْحَيِّ الْقَيُّومِ] <em>(ইবনে কাসীর-তাফসীর আয়াতুল কুরসী)</em></p>"}, {"fromVerse": 3, "toVerse": 3, "text": "<p>তিনি সত্যসহ তোমার প্রতি কিতাব অবতীর্ণ করেছেন,[১] যা ওর পূর্বের কিতাবের সমর্থক।</p><p>[১] অর্থাৎ, এটা যে আল্লাহর পক্ষ হতে অবতীর্ণ তাতে কোন সন্দেহ নেই। আর কিতাব বলতে কুরআন মাজীদ।</p>"}, {"fromVerse": 4, "toVerse": 4, "text": "<p>পূর্বে তিনি মানবজাতিকে সৎপথ প্রদর্শনের জন্য[১] তাওরাত ও ইঞ্জীল অবতীর্ণ করেছেন এবং তিনি ফুরক্বান (ন্যায়-অন্যায়ের মীমাংসাকারী; কুরআন) অবতীর্ণ করেছেন। [২] নিশ্চয় যারা আল্লাহর নিদর্শনাবলীকে অমান্য করে তাদের জন্য রয়েছে কঠোর শাস্তি। বস্তুতঃ আল্লাহ পরাক্রমশালী, প্রতিশোধ গ্রহণকারী।</p><p>[১] ইতিপূর্বে নবীদের উপর যে কিতাবসমূহ নাযিল হয়েছে, এই কিতাব সেগুলোর সত্যায়ন করে। অর্থাৎ, সে কিতাবগুলোতে যে কথাগুলো লিপিবদ্ধ ছিল, তার সত্যায়ন করে এবং তাতে যে সব ভবিষ্যদ্বাণী বর্ণিত হয়েছে, তা সত্য বলে স্বীকার করে। আর এর পরিষ্কার অর্থ হল, কুরআন কারীমও সেই সত্তার পক্ষ হতে অবতীর্ণ, যে সত্তা পূর্বেও বহু কিতাব নাযিল করেছেন। এটা যদি কোন অন্য পক্ষ হতে আসত অথবা মানুষের চেষ্টার ফল হত, তাহলে এর এবং উক্ত কিতাবগুলোর মধ্যে পারস্পরিক মিল থাকার পরিবর্তে অমিলই থাকত।</p><p>[২] অর্থাৎ, অবশ্যই তাওরাত এবং ইঞ্জীল সব সব সময়ে মানুষের হিদায়াতের উৎস ছিল। কারণ এগুলোর অবতীর্ণ হওয়ার উদ্দেশ্যই ছিল এটাই। এরপর 'তিনি ফুরকান অবতীর্ণ করেছেন' বলে এ কথা পরিষ্কার করে দিলেন যে, তাওরাত ও ইঞ্জীলের যামানা শেষ হয়ে গেছে। এখন তো কুরআন অবতীর্ণ হয়ে গেছে। আর কুরআনই হল ফুরকান এবং সত্য ও মিথ্যা জানার এটাই হল কষ্টিপাথর। এটাকে সত্য বলে বিশ্বাস না করলে আল্লাহর নিকট কেউ মুসলিম ও মু'মিন হতে পারবে না।</p>"}, {"fromVerse": 5, "toVerse": 5, "text": "<p>নিশ্চয়ই আল্লাহর কাছে দ্যুলোক-ভূলোকের কোন কিছুই গোপন নেই।</p>"}, {"fromVerse": 6, "toVerse": 6, "text": "<p>তিনিই মাতৃগর্ভে যেভাবে ইচ্ছা তোমাদের আকৃতি গঠন করেন। তিনি ব্যতীত অন্য কোন (সত্যিকার) উপাস্য নেই। [১] তিনি প্রবল পরাক্রমশালী, প্রজ্ঞাময়।</p><p>[১] সুশ্রী অথবা কুশ্রী, ছেলে অথবা মেয়ে, সৌভাগ্যবান অথবা দুর্ভাগ্যবান এবং পূর্ণাঙ্গ অথবা বিকলাঙ্গ ইত্যাদি বিচিত্রময়তা মায়ের গর্ভে যখন এককভাবে আল্লাহই সৃষ্টি করেন, তখন ঈসা (আঃ) ইলাহ কিভাবে হতে পারেন? তিনি নিজেও তো সৃষ্টির নানা পর্যায় অতিক্রম করে দুনিয়াতে এসেছেন। মহান আল্লাহ তাঁরও সৃষ্টি সম্পাদন করেছেন তাঁর মায়ের গর্ভে।</p>"}, {"fromVerse": 7, "toVerse": 7, "text": "<p>তিনিই তোমার প্রতি এই কিতাব (কুরআন) অবতীর্ণ করেছেন; যার কিছু আয়াত সুস্পষ্ট, দ্ব্যর্থহীন, এগুলি কিতাবের মূল অংশ; যার অন্যগুলি রূপক;[১] যাদের মনে বক্রতা আছে, তারা ফিতনা (বিশৃংখলা) সৃষ্টি ও ভুল ব্যাখ্যার উদ্দেশ্যে যা রূপক তার অনুসরণ করে। বস্তুতঃ আল্লাহ ব্যতীত অন্য কেউ এর ব্যাখ্যা জানে না।[২] আর যারা সুবিজ্ঞ তারা বলে, আমরা এ বিশ্বাস করি। সমস্তই আমাদের প্রতিপালকের নিকট থেকে আগত। বস্তুতঃ বুদ্ধিমান লোকেরাই উপদেশ গ্রহণ করে।</p><p>[১] مُحكَمَات (সুস্পষ্ট দ্ব্যর্থহীন) সেই আয়াতসমূহকে বলা হয় যাতে যাবতীয় আদেশ-নিষেধ, বিধি-বিধান, মাসলা-মাসায়েল এবং ইতিহাস ও কাহিনী আলোচিত হয়েছে; যার অর্থ স্পষ্ট ও দ্ব্যর্থহীন এবং যেগুলো বুঝতে কোন প্রকার অসুবিধা হয় না। আর مُتَشَابِهَات (রূপক) আয়াতগুলো এর বিপরীত। যেমন, আল্লাহর সত্তা, ভাগ্য সম্পর্কীয় বিষয়াদি, জান্নাত ও জাহান্নাম এবং ফিরিশতা ইত্যাদির ব্যাপার। অর্থাৎ, এমন বাস্তব জিনিস যার বাস্তবতা উপলব্ধি করতে মানুষের জ্ঞান-বুদ্ধি অপারগ অথবা যে ব্যাপারে এমন ব্যাখ্যা করার অবকাশ বা তাতে এমন অস্পষ্টতা ও দ্ব্যর্থতা থাকে যে, তার দ্বারা সাধারণ মানুষকে বিভ্রান্তি ও ভ্রষ্টতায় ফেলা সম্ভব হয়। এই কারণেই বলা হচ্ছে যে, যাদের অন্তরে বক্রতা থাকে, তারাই অস্পষ্ট আয়াতগুলোর পিছনে পড়ে থাকে এবং সেগুলোর মাধ্যমে ফিৎনা সৃষ্টি করে। যেমন খ্রিষ্টানদের অবস্থা; কুরআন ঈসা (আঃ)-কে আল্লাহর বান্দা এবং তাঁর রসূল বলেছে। এটা একটি পরিষ্কার ও দ্ব্যর্থহীন কথা। কিন্তু খ্রিষ্টানরা এটাকে বাদ দিয়ে কুরআনে যে ঈসা (আঃ)-কে 'রুহুল্লাহ' এবং 'কালিমাতুল্লাহ' বলা হয়েছে, সেটাকেই নিজেদের ভ্রষ্ট আকীদার দলীল হিসেবে গ্রহণ করেছে। অথচ তা ভুল। অনুরূপ অবস্থা বিদআতীদেরও; কুরআনের সুস্পষ্ট আকীদার বিপরীত বিদআতীরা যে ভ্রান্ত আকীদা গড়ে রেখেছে, তাও এই 'মুতাশাবিহাত' (অস্পষ্ট) আয়াতগুলোর ভিত্তিতেই। আবার কখনো নিজেদের দার্শনিক চিন্তাধারার কঠিন পেঁচ দ্বারা 'সুস্পষ্ট' আয়াতগুলোকে 'অস্পষ্ট' বানিয়ে ফেলে। (আল্লাহ আমাদেরকে এ কাজ হতে পানাহ দিন।) পক্ষান্তরে সঠিক আকীদা অবলম্বি মুসলিম 'সুস্পষ্ট' আয়াতগুলোর উপর আমল করে এবং 'অস্পষ্ট' আয়াতগুলোর ব্যাপারে সন্দেহ হলে, সেগুলোকে 'সুস্পষ্ট' আয়াতগুলোর আলোকে বুঝতে চেষ্টা করে। কেননা, কুরআন 'সুস্পষ্ট' আয়াতগুলোকেই কিতাবের 'মূল অংশ' বলে আখ্যায়িত করেছে। এর ফলে তারা ফিৎনা থেকে বেঁচে যায় এবং আকীদার বিভ্রান্তি থেকেও রেহাই পায়। আল্লাহ আমাদেরকে তাদের অন্তর্ভুক্ত করুন। আমীন।</p><p>[২] 'তা'বীল'-এর এক অর্থ হল, কোন জিনিসের আসল প্রকৃতত্ব, তত্ত্ব ও তাৎপর্য। এই অর্থের দিকে খেয়াল করে 'ইল্লাল্লা-হ' পড়ে থামা জরুরী। কারণ, প্রত্যেক জিনিসের আসল প্রকৃতত্ব স্পষ্টভাবে কেবল মহান আল্লাহই জানেন। 'তা'বীল'এর দ্বিতীয় অর্থ হল, কোন জিনিসের ব্যাখ্যা, অর্থপ্রকাশ এবং পরিষ্কারভাবে তা বর্ণনা করা। এই অর্থের দিক দিয়ে 'ইল্লাল্লা-হ' পড়ে না থেমে [وَالرَّاسِخُوْنَ فِي الْعِلْمِ] পড়ে থামা যায়। কারণ, গভীর জ্ঞানের অধিকারী ব্যক্তিরাও সঠিক ব্যাখ্যা এবং সুস্পষ্ট বর্ণনা দেওয়ার ক্ষমতা রাখেন। 'তা'বীল'এর এই উভয় অর্থ কুরআনে কারীমে ব্যবহূত হয়েছে। <em>(ইবনে কাসীর থেকে সারাংশ)</em></p>"}, {"fromVerse": 8, "toVerse": 8, "text": "<p>হে আমাদের প্রতিপালক! সরল পথ প্রদর্শনের পর তুমি আমাদের অন্তরকে বক্র করে দিও না এবং তোমার নিকট থেকে আমাদেরকে করুণা দান কর। নিশ্চয় তুমি মহাদাতা।</p>"}, {"fromVerse": 9, "toVerse": 9, "text": "<p>হে আমাদের প্রতিপালক! তুমি মানবজাতিকে একদিন একত্রে সমাবেশ করবে -- এতে কোন সন্দেহ নেই; নিশ্চয়ই আল্লাহ নির্ধারিত সময়ের ব্যতিক্রম (প্রতিশ্রুতি ভঙ্গ) করেন না।</p>"}, {"fromVerse": 10, "toVerse": 10, "text": "<p>যারা অবিশ্বাস করে তাদের ধনৈশ্বর্য ও সন্তান-সন্ততি আল্লাহর নিকট কোন কাজে লাগবে না। এবং এ সকল লোকই দোযখের ইন্ধন হবে।</p>"}]