{"39200":{"id":39200,"short_name":"Ashrs bin al-Hasan Shykh","full_name":"Ashrs bin al-Hasan Shykh","arabic":"أشرس بن الحسن","rank":4,"birth_date":"","birth_place":"","death_date":"","death_place":"","death_cause":"Natural","city":"","father_name":"","mother_name":"","interests":"4","bio":"*  *  *","children":"","siblings":"","spouses":"","teachers":"","students":"","kunya":""},"39201":{"id":39201,"short_name":"Anas bin Anis'h al-Rhawy","full_name":"Anas bin Anis'h al-Rhawy","arabic":"أنس بن أنيسة","rank":4,"birth_date":"","birth_place":"","death_date":"","death_place":"","death_cause":"Natural","city":"Bahrain,al-Syria","father_name":"","mother_name":"","interests":"4","bio":"الجزيرة,الشام * الرهاوي *  *","children":"","siblings":"","spouses":"","teachers":"","students":"","kunya":""},"39202":{"id":39202,"short_name":"Asad bin Yazid al-Bsry","full_name":"Asad bin Yazid al-Bsry","arabic":"أسد بن يزيد","rank":4,"birth_date":"","birth_place":"","death_date":"","death_place":"","death_cause":"Natural","city":"al-Basra,Khurasan","father_name":"","mother_name":"","interests":"4","bio":"البصري,الخراساني *  *  *","children":"","siblings":"","spouses":"","teachers":"","students":"","kunya":""},"39203":{"id":39203,"short_name":"Asad bin Rashid","full_name":"Asad bin Rashid","arabic":"أسد بن راشد","rank":4,"birth_date":"","birth_place":"","death_date":"","death_place":"","death_cause":"Natural","city":"Medina","father_name":"","mother_name":"","interests":"4","bio":"* الأنصاري *  *","children":"","siblings":"","spouses":"","teachers":"","students":"","kunya":""},"39204":{"id":39204,"short_name":"Asad bin Th'albah","full_name":"Asad bin Th'albah","arabic":"أسد بن ثعلبة","rank":4,"birth_date":"","birth_place":"","death_date":"238 AH","death_place":"","death_cause":"Natural","city":"Bahrain","father_name":"","mother_name":"","interests":"4","bio":"الجزيرة *  * مات سنة ثمان وثلاثين ومائتين *","children":"","siblings":"","spouses":"","teachers":"","students":"","kunya":""},"39205":{"id":39205,"short_name":"Art'ah bin Habib Shykh","full_name":"Art'ah bin Habib Shykh","arabic":"أرطأة بن حبيب","rank":4,"birth_date":"","birth_place":"","death_date":"","death_place":"","death_cause":"Natural","city":"al-Kufa","father_name":"","mother_name":"","interests":"4","bio":"الكوفي *  *  *","children":"","siblings":"","spouses":"","teachers":"","students":"","kunya":""},"39206":{"id":39206,"short_name":"Ubaid bin al-Aghr","full_name":"Ubaid bin al-Aghr","arabic":"أبيض بن الأغر","rank":4,"birth_date":"","birth_place":"","death_date":"","death_place":"","death_cause":"Natural","city":"","father_name":"","mother_name":"","interests":"4","bio":"*  *  *","children":"","siblings":"","spouses":"","teachers":"","students":"","kunya":""},"39207":{"id":39207,"short_name":"Ahyd bin Muhammad al-Wraq","full_name":"Ahyd bin Muhammad al-Wraq","arabic":"أحيد بن محمد","rank":4,"birth_date":"","birth_place":"","death_date":"","death_place":"","death_cause":"Natural","city":"Bulkh,Makkah","father_name":"","mother_name":"","interests":"4","bio":"بلخ,المكي *  *  *","children":"","siblings":"","spouses":"","teachers":"","students":"","kunya":""},"39208":{"id":39208,"short_name":"Ahyd bin al-Husain bin Ala","full_name":"Ahyd bin al-Husain bin Ala","arabic":"أحيد بن الحسين","rank":4,"birth_date":"","birth_place":"","death_date":"","death_place":"","death_cause":"Natural","city":"Bulkh,Makkah","father_name":"","mother_name":"","interests":"4","bio":"بلخ,المكي * السلمي *  * أبو محمد","children":"","siblings":"","spouses":"","teachers":"","students":"","kunya":"Abu Muhammad(أبو محمد)"},"39209":{"id":39209,"short_name":"Asrm bin Malik Abu 'Amr","full_name":"Asrm bin Malik Abu 'Amr","arabic":"أصرم بن مالك","rank":4,"birth_date":"","birth_place":"","death_date":"","death_place":"","death_cause":"Natural","city":"","father_name":"","mother_name":"","interests":"4","bio":"*  *  * أبو عمرو","children":"","siblings":"","spouses":"","teachers":"","students":"","kunya":"Abu 'Amr(أبو عمرو)"},"39210":{"id":39210,"short_name":"Bashr bin Mrzwq","full_name":"Bashr bin Mrzwq","arabic":"بشر بن مرزوق","rank":4,"birth_date":"","birth_place":"","death_date":"","death_place":"","death_cause":"Natural","city":"","father_name":"","mother_name":"","interests":"4","bio":"*  *  *","children":"","siblings":"","spouses":"","teachers":"","students":"","kunya":""},"39211":{"id":39211,"short_name":"Bashr bin Sryj al-Bzar","full_name":"Bashr bin Sryj al-Bzar","arabic":"بشر بن سريج","rank":4,"birth_date":"","birth_place":"","death_date":"","death_place":"","death_cause":"Natural","city":"al-Basra","father_name":"","mother_name":"","interests":"4","bio":"البصرة *  *  *","children":"","siblings":"","spouses":"","teachers":"","students":"","kunya":""},"39212":{"id":39212,"short_name":"Bashr bin Ubaid al-Darsa Abu","full_name":"Bashr bin Ubaid al-Darsa Abu","arabic":"بشر بن عبيد الدارسي","rank":4,"birth_date":"","birth_place":"","death_date":"","death_place":"","death_cause":"Natural","city":"al-Basra","father_name":"","mother_name":"","interests":"4","bio":"البصرة *  *  * أبو علي","children":"","siblings":"","spouses":"","teachers":"","students":"","kunya":"Abu 'Ali(أبو علي)"},"39213":{"id":39213,"short_name":"Bashr bin Abi al-Azhar Abu","full_name":"Bashr bin Abi al-Azhar Abu","arabic":"بشر بن أبي الأزهر","rank":4,"birth_date":"","birth_place":"","death_date":"","death_place":"","death_cause":"Natural","city":"Nisapur","father_name":"","mother_name":"","interests":"4","bio":"نيسابور *  *  * أبو الحسن","children":"","siblings":"","spouses":"","teachers":"","students":"","kunya":"Abu al-Hasan(أبو الحسن)"},"39214":{"id":39214,"short_name":"Bashr bin Hatm al-Rqa Skn","full_name":"Bashr bin Hatm al-Rqa Skn","arabic":"بشر بن حاتم الرقي","rank":4,"birth_date":"","birth_place":"","death_date":"224 AH","death_place":"","death_cause":"Natural","city":"al-Raqqa,al-Basra,al-Raqqa","father_name":"","mother_name":"","interests":"4","bio":"الرقي,البصرة,الرقي *  * مات في جمادي الأولي سنة أربع وعشرين ومائتين روى عنه البصريون *","children":"","siblings":"","spouses":"","teachers":"","students":"","kunya":""},"39215":{"id":39215,"short_name":"Bashr bin al-Mbark","full_name":"Bashr bin al-Mbark","arabic":"بشر بن المبارك","rank":4,"birth_date":"","birth_place":"","death_date":"","death_place":"","death_cause":"Natural","city":"al-Ta'if","father_name":"","mother_name":"","interests":"4","bio":"الطائفي *  *  *","children":"","siblings":"","spouses":"","teachers":"","students":"","kunya":""},"39216":{"id":39216,"short_name":"Bakr bin Muhammad al-Dby","full_name":"Bakr bin Muhammad al-Dby","arabic":"بكر بن محمد الضبي","rank":4,"birth_date":"","birth_place":"","death_date":"","death_place":"","death_cause":"Natural","city":"al-Basra","father_name":"","mother_name":"","interests":"4","bio":"البصرة * القرشي *  *","children":"","siblings":"","spouses":"","teachers":"","students":"","kunya":""},"39217":{"id":39217,"short_name":"Bakr bin Ayoub al-Skhtyany","full_name":"Bakr bin Ayoub al-Skhtyany","arabic":"بكر بن أيوب","rank":4,"birth_date":"","birth_place":"","death_date":"","death_place":"","death_cause":"Natural","city":"","father_name":"","mother_name":"","interests":"4","bio":"*  *  *","children":"","siblings":"","spouses":"","teachers":"","students":"","kunya":""},"39218":{"id":39218,"short_name":"Bakr bin Hmdan","full_name":"Bakr bin Hmdan","arabic":"بكر بن حمدان","rank":4,"birth_date":"","birth_place":"","death_date":"","death_place":"","death_cause":"Natural","city":"","father_name":"","mother_name":"","interests":"4","bio":"*  *  *","children":"","siblings":"","spouses":"","teachers":"","students":"","kunya":""},"39219":{"id":39219,"short_name":"Bakr bin Muhammad al-Abd","full_name":"Bakr bin Muhammad al-Abd","arabic":"بكر بن محمد العابد","rank":4,"birth_date":"","birth_place":"","death_date":"","death_place":"","death_cause":"Natural","city":"Sana'","father_name":"","mother_name":"","interests":"4","bio":"الصنعاني * الطائي,الحارثي,الحارثي *  *","children":"","siblings":"","spouses":"","teachers":"","students":"","kunya":""},"39220":{"id":39220,"short_name":"Bakr bin Sdqh Abu Sdqh","full_name":"Bakr bin Sdqh Abu Sdqh","arabic":"بكر بن صدقة","rank":4,"birth_date":"","birth_place":"","death_date":"","death_place":"","death_cause":"Natural","city":"Bulkh","father_name":"","mother_name":"","interests":"4","bio":"البلخي *  *  * أبو صدقة","children":"","siblings":"","spouses":"","teachers":"","students":"","kunya":"Abu Sdqh(أبو صدقة)"},"39221":{"id":39221,"short_name":"Bakr bin 'Abdullah al-Qaysy","full_name":"Bakr bin 'Abdullah al-Qaysy","arabic":"بكر بن عبد الله القيسي","rank":4,"birth_date":"","birth_place":"","death_date":"","death_place":"","death_cause":"Natural","city":"al-Basra","father_name":"","mother_name":"","interests":"4","bio":"البصرة * السدوسي *  *","children":"","siblings":"","spouses":"","teachers":"","students":"","kunya":""},"39222":{"id":39222,"short_name":"Bakr bin 'Isa Abu Bashr","full_name":"Bakr bin 'Isa Abu Bashr","arabic":"بكر بن عيسى","rank":4,"birth_date":"","birth_place":"","death_date":"","death_place":"","death_cause":"Natural","city":"al-Basra","father_name":"","mother_name":"","interests":"4","bio":"البصرة *  *  * أبو بشر","children":"","siblings":"","spouses":"","teachers":"","students":"","kunya":"Abu Bashr(أبو بشر)"},"39223":{"id":39223,"short_name":"Bakr bin Bhr al-Mra","full_name":"Bakr bin Bhr al-Mra","arabic":"بكر بن بحر","rank":4,"birth_date":"","birth_place":"","death_date":"","death_place":"","death_cause":"Natural","city":"","father_name":"","mother_name":"","interests":"4","bio":"*  *  *","children":"","siblings":"","spouses":"","teachers":"","students":"","kunya":""},"39224":{"id":39224,"short_name":"Bakr bin Ahmed bin Sa'id","full_name":"Bakr bin Ahmed bin Sa'id","arabic":"بكر بن أحمد بن سعيد","rank":4,"birth_date":"","birth_place":"","death_date":"","death_place":"","death_cause":"Natural","city":"Basra","father_name":"","mother_name":"","interests":"4","bio":"بصري *  *  *","children":"","siblings":"","spouses":"","teachers":"","students":"","kunya":""},"39225":{"id":39225,"short_name":"Bashyr bin 'Asim","full_name":"Bashyr bin 'Asim","arabic":"بشير بن عاصم","rank":4,"birth_date":"","birth_place":"","death_date":"","death_place":"","death_cause":"Natural","city":"Kufa","father_name":"","mother_name":"","interests":"4","bio":"الكوفة *  *  *","children":"","siblings":"","spouses":"","teachers":"","students":"","kunya":""},"39226":{"id":39226,"short_name":"Bashyr bin al-N'uman bin Aban","full_name":"Bashyr bin al-N'uman bin Aban","arabic":"بشير بن النعمان بن أبان","rank":4,"birth_date":"","birth_place":"","death_date":"","death_place":"","death_cause":"Natural","city":"","father_name":"","mother_name":"","interests":"4","bio":"*  *  * أبو محمد","children":"","siblings":"","spouses":"","teachers":"","students":"","kunya":"Abu Muhammad(أبو محمد)"},"39227":{"id":39227,"short_name":"Bkyr bin 'Ubaidullah bin Yahya","full_name":"Bkyr bin 'Ubaidullah bin Yahya","arabic":"بكير بن عبيد","rank":4,"birth_date":"","birth_place":"","death_date":"","death_place":"","death_cause":"Natural","city":"al-Basra","father_name":"","mother_name":"","interests":"4","bio":"البصرة *  *  *","children":"","siblings":"","spouses":"","teachers":"","students":"","kunya":""},"39228":{"id":39228,"short_name":"Bkar bin Hsyb al-Rama Bsra","full_name":"Bkar bin Hsyb al-Rama Bsra","arabic":"بكار بن حصيب","rank":4,"birth_date":"","birth_place":"","death_date":"","death_place":"","death_cause":"Natural","city":"Basra","father_name":"","mother_name":"","interests":"4","bio":"بصري *  *  *","children":"","siblings":"","spouses":"","teachers":"","students":"","kunya":""},"39229":{"id":39229,"short_name":"Blj bin Ziyad bin 'Isa","full_name":"Blj bin Ziyad bin 'Isa","arabic":"بلج بن زياد","rank":4,"birth_date":"","birth_place":"","death_date":"","death_place":"","death_cause":"Natural","city":"","father_name":"","mother_name":"","interests":"4","bio":"*  *  *","children":"","siblings":"","spouses":"","teachers":"","students":"","kunya":""},"39230":{"id":39230,"short_name":"Bhr bin Mhmwd al-Swna","full_name":"Bhr bin Mhmwd al-Swna","arabic":"بحر بن محمود","rank":4,"birth_date":"","birth_place":"","death_date":"","death_place":"","death_cause":"Natural","city":"","father_name":"","mother_name":"","interests":"4","bio":"*  *  *","children":"","siblings":"","spouses":"","teachers":"","students":"","kunya":""},"39231":{"id":39231,"short_name":"Bqyh bin Mhran Shykh","full_name":"Bqyh bin Mhran Shykh","arabic":"بقية بن مهران","rank":4,"birth_date":"","birth_place":"","death_date":"","death_place":"","death_cause":"Natural","city":"Baghdad","father_name":"","mother_name":"","interests":"4","bio":"بغداد *  *  *","children":"","siblings":"","spouses":"","teachers":"","students":"","kunya":""},"39232":{"id":39232,"short_name":"Bhmn al-Abd","full_name":"Bhmn al-Abd","arabic":"بهمن العابد","rank":4,"birth_date":"","birth_place":"","death_date":"","death_place":"","death_cause":"Natural","city":"al-Basra","father_name":"","mother_name":"","interests":"4","bio":"البصرة *  *  *","children":"","siblings":"","spouses":"","teachers":"","students":"","kunya":""},"39233":{"id":39233,"short_name":"Bdyl bin 'Amr bin Mus'ab","full_name":"Bdyl bin 'Amr bin Mus'ab","arabic":"بديل بن عمرو","rank":4,"birth_date":"","birth_place":"","death_date":"","death_place":"","death_cause":"Natural","city":"","father_name":"","mother_name":"","interests":"4","bio":"*  *  *","children":"","siblings":"","spouses":"","teachers":"","students":"","kunya":""},"39234":{"id":39234,"short_name":"Bstam bin Ja'far al-Azdy","full_name":"Bstam bin Ja'far al-Azdy","arabic":"بسطام بن جعفر","rank":4,"birth_date":"","birth_place":"","death_date":"","death_place":"","death_cause":"Natural","city":"","father_name":"","mother_name":"","interests":"4","bio":"* الأزدي *  *","children":"","siblings":"","spouses":"","teachers":"","students":"","kunya":""},"39235":{"id":39235,"short_name":"Tmym bin Abd al-Mu'mn al-Mrwzy","full_name":"Tmym bin Abd al-Mu'mn al-Mrwzy","arabic":"تميم بن عبد المؤمن","rank":4,"birth_date":"","birth_place":"","death_date":"","death_place":"","death_cause":"Natural","city":"","father_name":"","mother_name":"","interests":"4","bio":"*  *  *","children":"","siblings":"","spouses":"","teachers":"","students":"","kunya":""},"39236":{"id":39236,"short_name":"Tb' bin Khalid Imam Msjd","full_name":"Tb' bin Khalid Imam Msjd","arabic":"تبع بن خالد","rank":4,"birth_date":"","birth_place":"","death_date":"","death_place":"","death_cause":"Natural","city":"Tursus","father_name":"","mother_name":"","interests":"4","bio":"طرسوس *  *  *","children":"","siblings":"","spouses":"","teachers":"","students":"","kunya":""},"39237":{"id":39237,"short_name":"Twbh bin al-Smh","full_name":"Twbh bin al-Smh","arabic":"توبة بن الصمة","rank":4,"birth_date":"","birth_place":"","death_date":"","death_place":"","death_cause":"Natural","city":"al-Raqqa","father_name":"","mother_name":"","interests":"4","bio":"الرقة *  *  *","children":"","siblings":"","spouses":"","teachers":"","students":"","kunya":""},"39238":{"id":39238,"short_name":"Thwr bin 'Amr al-Qaysrana Abu","full_name":"Thwr bin 'Amr al-Qaysrana Abu","arabic":"ثور بن عمرو","rank":4,"birth_date":"","birth_place":"","death_date":"232 AH","death_place":"","death_cause":"Natural","city":"","father_name":"","mother_name":"","interests":"4","bio":"*  * مات سنة اثنتين وثلاثين ومائتين * أبو عمرو","children":"","siblings":"","spouses":"","teachers":"","students":"","kunya":"Abu 'Amr(أبو عمرو)"},"39239":{"id":39239,"short_name":"Ja'far bin Akrmh al-Quraishi","full_name":"Ja'far bin Akrmh al-Quraishi","arabic":"جعفر بن عكرمة","rank":4,"birth_date":"","birth_place":"","death_date":"","death_place":"","death_cause":"Natural","city":"Bulkh,Merv","father_name":"","mother_name":"","interests":"4","bio":"بلخ,مرو * القرشي *  *","children":"","siblings":"","spouses":"","teachers":"","students":"","kunya":""},"39240":{"id":39240,"short_name":"Ja'far bin Muhammad al-Fdyla al-Rs'ny","full_name":"Ja'far bin Muhammad al-Fdyla al-Rs'ny","arabic":"جعفر بن محمد الفضيلي","rank":4,"birth_date":"","birth_place":"","death_date":"","death_place":"","death_cause":"Natural","city":"Bahrain","father_name":"","mother_name":"","interests":"4","bio":"الجزيرة *  *  * أبو الفضل","children":"","siblings":"","spouses":"","teachers":"","students":"","kunya":"Abu Al-Fadl(أبو الفضل)"},"39241":{"id":39241,"short_name":"Ja'far bin Muhammad bin al-Hjaj","full_name":"Ja'far bin Muhammad bin al-Hjaj","arabic":"جعفر بن محمد بن الحجاج","rank":4,"birth_date":"","birth_place":"","death_date":"","death_place":"","death_cause":"Natural","city":"Kufa","father_name":"","mother_name":"","interests":"4","bio":"الكوفة *  *  *","children":"","siblings":"","spouses":"","teachers":"","students":"","kunya":""},"39242":{"id":39242,"short_name":"Ja'far bin Muhammad bin Sa'id","full_name":"Ja'far bin Muhammad bin Sa'id","arabic":"جعفر بن محمد بن سعيد","rank":4,"birth_date":"","birth_place":"","death_date":"","death_place":"","death_cause":"Natural","city":"Kufa","father_name":"","mother_name":"","interests":"4","bio":"الكوفة *  *  *","children":"","siblings":"","spouses":"","teachers":"","students":"","kunya":""},"39243":{"id":39243,"short_name":"Ja'far bin Muhammad bin Ja'far","full_name":"Ja'far bin Muhammad bin Ja'far","arabic":"جعفر بن محمد بن جعفر المدائني","rank":4,"birth_date":"","birth_place":"","death_date":"","death_place":"","death_cause":"Natural","city":"Mada'in,Wasit","father_name":"","mother_name":"","interests":"4","bio":"المدائني,واسط *  *  *","children":"","siblings":"","spouses":"","teachers":"","students":"","kunya":""},"39244":{"id":39244,"short_name":"Ja'far bin Muhammad al-Qlasa","full_name":"Ja'far bin Muhammad al-Qlasa","arabic":"جعفر بن محمد القلاسي","rank":4,"birth_date":"","birth_place":"","death_date":"","death_place":"","death_cause":"Natural","city":"al-Ramla","father_name":"","mother_name":"","interests":"4","bio":"الرملة *  *  *","children":"","siblings":"","spouses":"","teachers":"","students":"","kunya":""},"39245":{"id":39245,"short_name":"Jra bin 'Abdul 'Aziz","full_name":"Jra bin 'Abdul 'Aziz","arabic":"جري بن عبد العزيز","rank":4,"birth_date":"","birth_place":"","death_date":"","death_place":"","death_cause":"Natural","city":"","father_name":"","mother_name":"","interests":"4","bio":"*  *  *","children":"","siblings":"","spouses":"","teachers":"","students":"","kunya":""},"39246":{"id":39246,"short_name":"Jra bin Shdad bin Sbyh","full_name":"Jra bin Shdad bin Sbyh","arabic":"جري بن شداد","rank":4,"birth_date":"","birth_place":"","death_date":"","death_place":"","death_cause":"Natural","city":"al-Ramla,Asbahan","father_name":"","mother_name":"","interests":"4","bio":"الرملة,الأصبهاني *  *  *","children":"","siblings":"","spouses":"","teachers":"","students":"","kunya":""},"39247":{"id":39247,"short_name":"Jmhwr bin Mnswr","full_name":"Jmhwr bin Mnswr","arabic":"جمهور بن منصور","rank":4,"birth_date":"","birth_place":"","death_date":"","death_place":"","death_cause":"Natural","city":"","father_name":"","mother_name":"","interests":"4","bio":"* الحضرمي *  *","children":"","siblings":"","spouses":"","teachers":"","students":"","kunya":""},"39248":{"id":39248,"short_name":"al-Jnyd bin Bhram al-Rjana","full_name":"al-Jnyd bin Bhram al-Rjana","arabic":"الجنيد بن بهرام","rank":4,"birth_date":"","birth_place":"","death_date":"","death_place":"","death_cause":"Natural","city":"","father_name":"","mother_name":"","interests":"4","bio":"*  *  *","children":"","siblings":"","spouses":"","teachers":"","students":"","kunya":""},"39249":{"id":39249,"short_name":"al-Hasan bin Muhammad al-Lythy Abu","full_name":"al-Hasan bin Muhammad al-Lythy Abu","arabic":"الحسن بن محمد الليثي","rank":4,"birth_date":"","birth_place":"","death_date":"","death_place":"","death_cause":"Natural","city":"Bulkh,Merv,Merv","father_name":"","mother_name":"","interests":"4","bio":"البلخي,مرو,مرو * الليثي *  * أبو محمد","children":"","siblings":"","spouses":"","teachers":"","students":"","kunya":"Abu Muhammad(أبو محمد)"},"39250":{"id":39250,"short_name":"al-Hasan bin Ziyad al-Lu'Lu'i","full_name":"al-Hasan bin Ziyad al-Lu'Lu'i","arabic":"الحسن بن زياد اللؤلؤي","rank":4,"birth_date":"","birth_place":"","death_date":"~204 AH","death_place":"","death_cause":"Natural","city":"Kufa, Baghdad","father_name":"","mother_name":"","interests":"4,5","bio":"","children":"","siblings":"","spouses":"","teachers":"","students":"","kunya":"Abu 'Ali"},"39251":{"id":39251,"short_name":"al-Hasan bin Ibrahim Abu Hatm","full_name":"al-Hasan bin Ibrahim Abu Hatm","arabic":"الحسن بن إبراهيم","rank":4,"birth_date":"","birth_place":"","death_date":"","death_place":"","death_cause":"Natural","city":"","father_name":"","mother_name":"","interests":"4","bio":"*  *  * أبو حاتم","children":"","siblings":"","spouses":"","teachers":"","students":"","kunya":"Abu Hatm(أبو حاتم)"},"39252":{"id":39252,"short_name":"al-Hasan bin 'Uthman Qada Bkhara","full_name":"al-Hasan bin 'Uthman Qada Bkhara","arabic":"الحسن بن عثمان قاضي","rank":4,"birth_date":"","birth_place":"","death_date":"","death_place":"","death_cause":"Natural","city":"","father_name":"","mother_name":"","interests":"4","bio":"* قاضي *  *","children":"","siblings":"","spouses":"","teachers":"","students":"","kunya":""},"39253":{"id":39253,"short_name":"al-Hasan bin Nsr bin al-Husain","full_name":"al-Hasan bin Nsr bin al-Husain","arabic":"الحسن بن نصر","rank":4,"birth_date":"","birth_place":"","death_date":"","death_place":"","death_cause":"Natural","city":"Merv,Merv","father_name":"","mother_name":"","interests":"4","bio":"مرو,مرو *  *  * أبو شداد","children":"","siblings":"","spouses":"","teachers":"","students":"","kunya":"Abu Shdad(أبو شداد)"},"39254":{"id":39254,"short_name":"al-Hasan bin Ala bin Muslim","full_name":"al-Hasan bin Ala bin Muslim","arabic":"الحسن بن علي بن مسلم","rank":4,"birth_date":"","birth_place":"","death_date":"","death_place":"","death_cause":"Natural","city":"al-Hims","father_name":"","mother_name":"","interests":"4","bio":"الحمصي *  *  * أبو عتبة","children":"","siblings":"","spouses":"","teachers":"","students":"","kunya":"Abu 'Utba(أبو عتبة)"},"39255":{"id":39255,"short_name":"al-Hasan bin Sufyan Imam Msjd","full_name":"al-Hasan bin Sufyan Imam Msjd","arabic":"الحسن بن سفيان إمام","rank":4,"birth_date":"","birth_place":"","death_date":"","death_place":"","death_cause":"Natural","city":"Tursus","father_name":"","mother_name":"","interests":"4","bio":"طرسوس *  *  *","children":"","siblings":"","spouses":"","teachers":"","students":"","kunya":""},"39256":{"id":39256,"short_name":"al-Hasan bin S'hrb","full_name":"al-Hasan bin S'hrb","arabic":"الحسن بن سهرب","rank":4,"birth_date":"","birth_place":"","death_date":"226 AH","death_place":"","death_cause":"Natural","city":"Bulkh","father_name":"","mother_name":"","interests":"4","bio":"بلخ *  * مات سنة ست وعشرين ومائتين وكان متقنا وكنيته أبو علي *","children":"","siblings":"","spouses":"","teachers":"","students":"","kunya":""},"39257":{"id":39257,"short_name":"al-Hasan bin Abi Yazid al-Kwfa","full_name":"al-Hasan bin Abi Yazid al-Kwfa","arabic":"الحسن بن أبي يزيد الكوفي","rank":4,"birth_date":"","birth_place":"","death_date":"","death_place":"","death_cause":"Natural","city":"al-Kufa,al-Kufa","father_name":"","mother_name":"","interests":"4","bio":"الكوفي,الكوفي *  *  *","children":"","siblings":"","spouses":"","teachers":"","students":"","kunya":""},"39258":{"id":39258,"short_name":"al-Hasan bin Ziyad al-Mharby Knyt'h","full_name":"al-Hasan bin Ziyad al-Mharby Knyt'h","arabic":"الحسن بن زياد المحاربي","rank":4,"birth_date":"","birth_place":"","death_date":"","death_place":"","death_cause":"Natural","city":"Kufa","father_name":"","mother_name":"","interests":"4","bio":"الكوفة *  *  * أبو علي","children":"","siblings":"","spouses":"","teachers":"","students":"","kunya":"Abu 'Ali(أبو علي)"},"39259":{"id":39259,"short_name":"al-Hasan bin Khalid al-Yshkry","full_name":"al-Hasan bin Khalid al-Yshkry","arabic":"الحسن بن خالد","rank":4,"birth_date":"","birth_place":"","death_date":"","death_place":"","death_cause":"Natural","city":"","father_name":"","mother_name":"","interests":"4","bio":"*  *  *","children":"","siblings":"","spouses":"","teachers":"","students":"","kunya":""},"39260":{"id":39260,"short_name":"al-Hasan bin Muhammad al-Krabysy","full_name":"al-Hasan bin Muhammad al-Krabysy","arabic":"الحسن بن محمد الكرابيسي","rank":4,"birth_date":"","birth_place":"","death_date":"","death_place":"","death_cause":"Natural","city":"al-Basra","father_name":"","mother_name":"","interests":"4","bio":"البصرة *  *  *","children":"","siblings":"","spouses":"","teachers":"","students":"","kunya":""},"39261":{"id":39261,"short_name":"al-Hasan bin Muhammad al-Mrwzy","full_name":"al-Hasan bin Muhammad al-Mrwzy","arabic":"الحسن بن محمد المروزي","rank":4,"birth_date":"","birth_place":"","death_date":"","death_place":"","death_cause":"Natural","city":"Khurasan","father_name":"","mother_name":"","interests":"4","bio":"خراسان *  *  *","children":"","siblings":"","spouses":"","teachers":"","students":"","kunya":""},"39262":{"id":39262,"short_name":"al-Hasan bin Ala al-Hlwany Abu","full_name":"al-Hasan bin Ala al-Hlwany Abu","arabic":"الحسن بن علي الحلواني","rank":4,"birth_date":"","birth_place":"","death_date":"270 AH","death_place":"","death_cause":"Natural","city":"","father_name":"","mother_name":"","interests":"4","bio":"*  * مات في ذي الحجة سنة ثلاثين وأربعين ومائتين * أبو محمد","children":"","siblings":"","spouses":"","teachers":"","students":"","kunya":"Abu Muhammad(أبو محمد)"},"39263":{"id":39263,"short_name":"al-Hasan bin Sahl al-J'fy Abu","full_name":"al-Hasan bin Sahl al-J'fy Abu","arabic":"الحسن بن سهل الجعفي","rank":4,"birth_date":"","birth_place":"","death_date":"","death_place":"","death_cause":"Natural","city":"Kufa","father_name":"","mother_name":"","interests":"4","bio":"الكوفة *  *  * أبو علي","children":"","siblings":"","spouses":"","teachers":"","students":"","kunya":"Abu 'Ali(أبو علي)"},"39264":{"id":39264,"short_name":"al-Hasan bin Salah al-Bzar","full_name":"al-Hasan bin Salah al-Bzar","arabic":"الحسن بن صالح البزار","rank":4,"birth_date":"","birth_place":"","death_date":"","death_place":"","death_cause":"Natural","city":"Wasit","father_name":"","mother_name":"","interests":"4","bio":"واسط *  *  *","children":"","siblings":"","spouses":"","teachers":"","students":"","kunya":""},"39265":{"id":39265,"short_name":"al-Hasan bin Isra'iyl","full_name":"al-Hasan bin Isra'iyl","arabic":"الحسن بن إسرائيل","rank":4,"birth_date":"","birth_place":"","death_date":"","death_place":"","death_cause":"Natural","city":"","father_name":"","mother_name":"","interests":"4","bio":"*  *  *","children":"","siblings":"","spouses":"","teachers":"","students":"","kunya":""},"39266":{"id":39266,"short_name":"al-Hasan bin Harun","full_name":"al-Hasan bin Harun","arabic":"الحسن بن هارون","rank":4,"birth_date":"","birth_place":"","death_date":"","death_place":"","death_cause":"Natural","city":"Nisapur,Makkah","father_name":"","mother_name":"","interests":"4","bio":"نيسابور,مكي *  *  *","children":"","siblings":"","spouses":"","teachers":"","students":"","kunya":""},"39267":{"id":39267,"short_name":"al-Hasan bin al-Skyn al-Bldy","full_name":"al-Hasan bin al-Skyn al-Bldy","arabic":"الحسن بن السكين","rank":4,"birth_date":"","birth_place":"","death_date":"","death_place":"","death_cause":"Natural","city":"","father_name":"","mother_name":"","interests":"4","bio":"* العبدي *  *","children":"","siblings":"","spouses":"","teachers":"","students":"","kunya":""},"39268":{"id":39268,"short_name":"al-Hasan bin Ibrahim bin Musa","full_name":"al-Hasan bin Ibrahim bin Musa","arabic":"الحسن بن إبراهيم بن موسى","rank":4,"birth_date":"","birth_place":"","death_date":"","death_place":"","death_cause":"Natural","city":"al-Baghdad,Makkah","father_name":"","mother_name":"","interests":"4","bio":"البغدادي,مكة *  *  * أبو علي","children":"","siblings":"","spouses":"","teachers":"","students":"","kunya":"Abu 'Ali(أبو علي)"},"39269":{"id":39269,"short_name":"al-Hasan bin al-Khlyl al-Hlby","full_name":"al-Hasan bin al-Khlyl al-Hlby","arabic":"الحسن بن الخليل","rank":4,"birth_date":"","birth_place":"","death_date":"","death_place":"","death_cause":"Natural","city":"","father_name":"","mother_name":"","interests":"4","bio":"*  *  *","children":"","siblings":"","spouses":"","teachers":"","students":"","kunya":""},"39270":{"id":39270,"short_name":"al-Hasan bin Ala al-Maymuny Abu","full_name":"al-Hasan bin Ala al-Maymuny Abu","arabic":"الحسن بن علي الميموني","rank":4,"birth_date":"","birth_place":"","death_date":"","death_place":"","death_cause":"Natural","city":"","father_name":"","mother_name":"","interests":"4","bio":"*  *  * أبو علي","children":"","siblings":"","spouses":"","teachers":"","students":"","kunya":"Abu 'Ali(أبو علي)"},"39271":{"id":39271,"short_name":"al-Hasan bin Salam al-Swaq Bghdady","full_name":"al-Hasan bin Salam al-Swaq Bghdady","arabic":"الحسن بن سلام","rank":4,"birth_date":"","birth_place":"","death_date":"","death_place":"","death_cause":"Natural","city":"","father_name":"","mother_name":"","interests":"4","bio":"* الثقفي *  *","children":"","siblings":"","spouses":"","teachers":"","students":"","kunya":""},"39272":{"id":39272,"short_name":"al-Hasan bin 'Abdur Rahman al-Ahtyata","full_name":"al-Hasan bin 'Abdur Rahman al-Ahtyata","arabic":"الحسن بن عبد الرحمن الاحتياطي","rank":4,"birth_date":"","birth_place":"","death_date":"","death_place":"","death_cause":"Natural","city":"Bahrain,Medina","father_name":"","mother_name":"","interests":"4","bio":"الجزيرة,المدني *  *  *","children":"","siblings":"","spouses":"","teachers":"","students":"","kunya":""},"39273":{"id":39273,"short_name":"al-Hasan bin Thwab Shykh","full_name":"al-Hasan bin Thwab Shykh","arabic":"الحسن بن ثواب","rank":4,"birth_date":"","birth_place":"","death_date":"","death_place":"","death_cause":"Natural","city":"","father_name":"","mother_name":"","interests":"4","bio":"*  *  *","children":"","siblings":"","spouses":"","teachers":"","students":"","kunya":""},"39274":{"id":39274,"short_name":"al-Hasan bin Muhammad bin al-Harith","full_name":"al-Hasan bin Muhammad bin al-Harith","arabic":"الحسن بن محمد بن الحارث","rank":4,"birth_date":"","birth_place":"","death_date":"","death_place":"","death_cause":"Natural","city":"","father_name":"","mother_name":"","interests":"4","bio":"*  *  *","children":"","siblings":"","spouses":"","teachers":"","students":"","kunya":""},"39275":{"id":39275,"short_name":"al-Hasan bin Mkrm bin Hsan","full_name":"al-Hasan bin Mkrm bin Hsan","arabic":"الحسن بن مكرم","rank":4,"birth_date":"","birth_place":"","death_date":"","death_place":"","death_cause":"Natural","city":"Baghdad","father_name":"","mother_name":"","interests":"4","bio":"بغداد *  *  *","children":"","siblings":"","spouses":"","teachers":"","students":"","kunya":""},"39276":{"id":39276,"short_name":"al-Hasan bin Abi Umayya al-Bghdady","full_name":"al-Hasan bin Abi Umayya al-Bghdady","arabic":"الحسن بن أبي أمية","rank":4,"birth_date":"","birth_place":"","death_date":"","death_place":"","death_cause":"Natural","city":"al-Baghdad,Antioch,Antioch","father_name":"","mother_name":"","interests":"4","bio":"البغدادي,أنطاكية,أنطاكية *  *  *","children":"","siblings":"","spouses":"","teachers":"","students":"","kunya":""},"39277":{"id":39277,"short_name":"al-Hasan bin Sahl al-Khyat","full_name":"al-Hasan bin Sahl al-Khyat","arabic":"الحسن بن سهل الخياط","rank":4,"birth_date":"","birth_place":"","death_date":"","death_place":"","death_cause":"Natural","city":"","father_name":"","mother_name":"","interests":"4","bio":"* الحضرمي *  *","children":"","siblings":"","spouses":"","teachers":"","students":"","kunya":""},"39278":{"id":39278,"short_name":"al-Harith bin 'Umar","full_name":"al-Harith bin 'Umar","arabic":"الحارث بن عمر","rank":4,"birth_date":"","birth_place":"","death_date":"","death_place":"","death_cause":"Natural","city":"","father_name":"","mother_name":"","interests":"4","bio":"* مولى *  *","children":"","siblings":"","spouses":"","teachers":"","students":"","kunya":""},"39279":{"id":39279,"short_name":"al-Harith bin Sulaiman al-Rmly Abu","full_name":"al-Harith bin Sulaiman al-Rmly Abu","arabic":"الحارث بن سليمان الرملي","rank":4,"birth_date":"","birth_place":"","death_date":"","death_place":"","death_cause":"Natural","city":"al-Ramla","father_name":"","mother_name":"","interests":"4","bio":"الرملي *  *  * أبو سليمان","children":"","siblings":"","spouses":"","teachers":"","students":"","kunya":"Abu Sulaiman(أبو سليمان)"},"39280":{"id":39280,"short_name":"Husayn bin 'Imran al-Jhny","full_name":"Husayn bin 'Imran al-Jhny","arabic":"حسين بن عمران الجهني","rank":4,"birth_date":"","birth_place":"","death_date":"","death_place":"","death_cause":"Natural","city":"","father_name":"","mother_name":"","interests":"4","bio":"* الجهني *  *","children":"","siblings":"","spouses":"","teachers":"","students":"","kunya":""},"39281":{"id":39281,"short_name":"Husayn bin Habib al-Ymamy","full_name":"Husayn bin Habib al-Ymamy","arabic":"حسين بن حبيب","rank":4,"birth_date":"","birth_place":"","death_date":"","death_place":"","death_cause":"Natural","city":"al-Yamama","father_name":"","mother_name":"","interests":"4","bio":"اليمامي *  *  *","children":"","siblings":"","spouses":"","teachers":"","students":"","kunya":""},"39282":{"id":39282,"short_name":"Husayn bin Husayn al-'Ashqr Abu","full_name":"Husayn bin Husayn al-'Ashqr Abu","arabic":"حسين بن حسين الأشقر","rank":4,"birth_date":"","birth_place":"","death_date":"","death_place":"","death_cause":"Natural","city":"","father_name":"","mother_name":"","interests":"4","bio":"* الفزاري *  * أبو عبد الله","children":"","siblings":"","spouses":"","teachers":"","students":"","kunya":"Abu 'Abdullah(أبو عبد الله)"},"39283":{"id":39283,"short_name":"Husayn bin 'Abdullah","full_name":"Husayn bin 'Abdullah","arabic":"حسين بن عبد الله","rank":4,"birth_date":"","birth_place":"","death_date":"","death_place":"","death_cause":"Natural","city":"Nisapur","father_name":"","mother_name":"","interests":"4","bio":"نيسابور *  *  *","children":"","siblings":"","spouses":"","teachers":"","students":"","kunya":""},"39284":{"id":39284,"short_name":"Husayn bin Muhammad","full_name":"Husayn bin Muhammad","arabic":"حسين بن محمد","rank":4,"birth_date":"","birth_place":"","death_date":"","death_place":"","death_cause":"Natural","city":"","father_name":"","mother_name":"","interests":"4","bio":"*  *  *","children":"","siblings":"","spouses":"","teachers":"","students":"","kunya":""},"39285":{"id":39285,"short_name":"Husayn bin 'Isa al-Hnfy","full_name":"Husayn bin 'Isa al-Hnfy","arabic":"حسين بن عيسى الحنفي","rank":4,"birth_date":"","birth_place":"","death_date":"","death_place":"","death_cause":"Natural","city":"","father_name":"","mother_name":"","interests":"4","bio":"* الحنفي *  *","children":"","siblings":"","spouses":"","teachers":"","students":"","kunya":""},"39286":{"id":39286,"short_name":"Husayn bin al-Dhak","full_name":"Husayn bin al-Dhak","arabic":"حسين بن الضحاك","rank":4,"birth_date":"","birth_place":"","death_date":"","death_place":"","death_cause":"Natural","city":"Nisapur","father_name":"","mother_name":"","interests":"4","bio":"نيسابور * الهاشمي *  *","children":"","siblings":"","spouses":"","teachers":"","students":"","kunya":""},"39287":{"id":39287,"short_name":"Husayn bin 'Amr bin Muhammad","full_name":"Husayn bin 'Amr bin Muhammad","arabic":"الحسين بن عمرو بن محمد العنقزي","rank":4,"birth_date":"","birth_place":"","death_date":"","death_place":"","death_cause":"Natural","city":"Kufa","father_name":"","mother_name":"","interests":"4","bio":"","children":"","siblings":"","spouses":"","teachers":"","students":"","kunya":""},"39288":{"id":39288,"short_name":"Husayn bin Ma'mr bin 'Umar","full_name":"Husayn bin Ma'mr bin 'Umar","arabic":"حسين بن معمر","rank":4,"birth_date":"","birth_place":"","death_date":"","death_place":"","death_cause":"Natural","city":"al-Basra","father_name":"","mother_name":"","interests":"4","bio":"البصري * المازني,العنبري,الحضرمي *  *","children":"","siblings":"","spouses":"","teachers":"","students":"","kunya":""},"39289":{"id":39289,"short_name":"Husayn bin Qz'h al-Bahla Abu","full_name":"Husayn bin Qz'h al-Bahla Abu","arabic":"حسين بن قزعة","rank":4,"birth_date":"","birth_place":"","death_date":"","death_place":"","death_cause":"Natural","city":"Medina","father_name":"","mother_name":"","interests":"4","bio":"* الأنصاري *  * أبو الحسن","children":"","siblings":"","spouses":"","teachers":"","students":"","kunya":"Abu al-Hasan(أبو الحسن)"},"39290":{"id":39290,"short_name":"Husayn bin Muhammad bin Abi Ma'shar","full_name":"Husayn bin Muhammad bin Abi Ma'shar al-Sundi","arabic":"الحسين بن محمد بن أبى معشر السندي","rank":4,"birth_date":"","birth_place":"","death_date":"","death_place":"","death_cause":"Natural","city":"Medina","father_name":"","mother_name":"","interests":"4","bio":"","children":"","siblings":"","spouses":"","teachers":"","students":"","kunya":""},"39291":{"id":39291,"short_name":"Husayn bin Muhammad Mhyar al-Hafz","full_name":"Husayn bin Muhammad Mhyar al-Hafz","arabic":"حسين بن محمد مهيار","rank":4,"birth_date":"","birth_place":"","death_date":"","death_place":"","death_cause":"Natural","city":"al-Basra","father_name":"","mother_name":"","interests":"4","bio":"البصرة *  *  *","children":"","siblings":"","spouses":"","teachers":"","students":"","kunya":""},"39293":{"id":39293,"short_name":"Husayn bin S'aid al-Mkhrmy Bghdady","full_name":"Husayn bin S'aid al-Mkhrmy Bghdady","arabic":"حسين بن سعيد","rank":4,"birth_date":"","birth_place":"","death_date":"","death_place":"","death_cause":"Natural","city":"","father_name":"","mother_name":"","interests":"4","bio":"* مولى *  *","children":"","siblings":"","spouses":"","teachers":"","students":"","kunya":""},"39294":{"id":39294,"short_name":"Husayn bin al-Hasan bin Hrb","full_name":"Husayn bin al-Hasan bin Hrb","arabic":"حسين بن الحسن بن حرب","rank":4,"birth_date":"","birth_place":"","death_date":"before  296 AH","death_place":"","death_cause":"Natural","city":"","father_name":"","mother_name":"","interests":"4","bio":"* القاضي * مات قبل الخمسين في سنة ست وأربعين ومائتين * أبو عبد الله","children":"","siblings":"","spouses":"","teachers":"","students":"","kunya":"Abu 'Abdullah(أبو عبد الله)"},"39295":{"id":39295,"short_name":"Husayn bin Muhammad al-Hjby","full_name":"Husayn bin Muhammad al-Hjby","arabic":"حسين بن محمد الحجبي","rank":4,"birth_date":"","birth_place":"","death_date":"","death_place":"","death_cause":"Natural","city":"","father_name":"","mother_name":"","interests":"4","bio":"*  *  *","children":"","siblings":"","spouses":"","teachers":"","students":"","kunya":""},"39296":{"id":39296,"short_name":"Husayn bin 'Abdullah bin Hmran","full_name":"Husayn bin 'Abdullah bin Hmran","arabic":"حسين بن عبد الله بن حمران","rank":4,"birth_date":"","birth_place":"","death_date":"","death_place":"","death_cause":"Natural","city":"al-Raqqa,Asbahan","father_name":"","mother_name":"","interests":"4","bio":"الرقي,الأصبهاني * الخزرجي *  *","children":"","siblings":"","spouses":"","teachers":"","students":"","kunya":""},"39297":{"id":39297,"short_name":"Husayn bin Abi Zayd al-Dbagh","full_name":"Husayn bin Abi Zayd al-Dbagh","arabic":"حسين بن أبي زيد","rank":4,"birth_date":"","birth_place":"","death_date":"254 AH","death_place":"","death_cause":"Natural","city":"","father_name":"","mother_name":"","interests":"4","bio":"*  * مات سنة أربع وخمسين ومائتين *","children":"","siblings":"","spouses":"","teachers":"","students":"","kunya":""},"39298":{"id":39298,"short_name":"Husayn bin Bhr al-Ahwazy Abu","full_name":"Husayn bin Bhr al-Ahwazy Abu","arabic":"حسين بن بحر","rank":4,"birth_date":"","birth_place":"","death_date":"261 AH","death_place":"","death_cause":"Natural","city":"","father_name":"","mother_name":"","interests":"4","bio":"*  * مات بملطية سنة إحدي وستين ومائتين * أبو عبد الله","children":"","siblings":"","spouses":"","teachers":"","students":"","kunya":"Abu 'Abdullah(أبو عبد الله)"},"39299":{"id":39299,"short_name":"Husayn bin Ma'dan al-Farsy","full_name":"Husayn bin Ma'dan al-Farsy","arabic":"حسين بن معدان","rank":4,"birth_date":"","birth_place":"","death_date":"","death_place":"","death_cause":"Natural","city":"","father_name":"","mother_name":"","interests":"4","bio":"*  *  *","children":"","siblings":"","spouses":"","teachers":"","students":"","kunya":""}}